setup.cfg
setup.py
tnot/__init__.py
tnot/exc.py
tnot/tnot.py
tnot.egg-info/PKG-INFO
tnot.egg-info/SOURCES.txt
tnot.egg-info/dependency_links.txt
tnot.egg-info/top_level.txt